flounder/__init__.py
flounder/flounder.py
flounder-0.0.7.dist-info/DESCRIPTION.rst
flounder-0.0.7.dist-info/METADATA
flounder-0.0.7.dist-info/RECORD
flounder-0.0.7.dist-info/WHEEL
flounder-0.0.7.dist-info/metadata.json
flounder-0.0.7.dist-info/top_level.txt
