Metadata-Version: 2.0
Name: flounder
Version: 0.0.7
Summary: flounder is a library that create Entity of Dialogflow. This library uses RestAPI of dialogflow. It is not an official library.
Home-page: https://github.com/flatfisher/flounder
Author: flatfisher
Author-email: shimano.entou@gmail.com
License: MIT
Keywords: dialogflow,dialogflow entity
Platform: UNKNOWN
Classifier: Programming Language :: Python :: 2.7
Requires-Dist: requests (==2.18.4)
